{"cameraMode":{"drawMode":0,"name":"Shaded","section":"Shading Mode"},"sceneLighting":true,"audioPlay":false,"sceneViewState":{"m_AlwaysRefresh":false,"showFog":true,"showSkybox":true,"showFlares":true,"showImageEffects":true,"showParticleSystems":true,"showVisualEffectGraphs":true,"m_FxEnabled":true},"in2DMode":false,"pivot":{"x":595.0234375,"y":313.9409484863281,"z":3154.553466796875},"rotation":{"x":-0.007179930806159973,"y":0.005370231345295906,"z":0.0012141431216150523,"w":1.0009007453918458},"size":2290.09033203125,"orthographic":false}